vcvf_emotion/__init__.py
vcvf_emotion/face_emotion.py
vcvf_emotion/test.jpg
vcvf_emotion/face_utils/__init__.py
vcvf_emotion/face_utils/facealigner.py
vcvf_emotion/face_utils/helpers.py
vcvf_emotion/models/happymodle.json
vcvf_emotion/models/weights.best.hdf5
vcvf_emotion-0.0.0.4.dist-info/DESCRIPTION.rst
vcvf_emotion-0.0.0.4.dist-info/METADATA
vcvf_emotion-0.0.0.4.dist-info/RECORD
vcvf_emotion-0.0.0.4.dist-info/WHEEL
vcvf_emotion-0.0.0.4.dist-info/entry_points.txt
vcvf_emotion-0.0.0.4.dist-info/metadata.json
vcvf_emotion-0.0.0.4.dist-info/top_level.txt
